Workbook
Name Slicer_Category: #N/A
Name Slicer_Months__Date: #N/A
Name Slicer_Region: #N/A

Sheet Project_Instructions
A1: Dataset: Use the 'Final Project Dataset' sheet containing 200+ records of customer transactions.
A3: Objective:
A4: Create a full-fledged analysis and reporting solution using Excel to analyze customer transactions, find insights,
A5: and build visualizations and dashboards.
A7: Key Topics to Implement:
A8: - Date & Time Functions: TODAY, NOW, DATEDIF, EOMONTH
A9: - FILTER Function for multi-value returns
A10: - Conditional Formatting with Icons/Arrows
A11: - Create Timestamp (using NOW and iterative calculations)
A12: - WHAT-IF Analysis: Scenario Manager, Goal Seek
A13: - Linear Regression using Data Analysis Toolpak
A14: - Data Analysis & Storytelling from the dataset
... A29: - Use of all required formulas and functions as listed above

Sheet DASHBOARD
L1: DASHBOARD - FINAL PROJECT
B14: TOTAL AMOUNT
B16: =SUM(Final_Project_Dataset!N2:N251) -> 229192.47

Sheet Final_Project_Dataset
A1: Transaction_ID | B1: Date | C1: Customer_ID | D1: Customer_Name | E1: Product_ID | F1: Product_Name | G1: Category | H1: Quantity | I1: Unit_Price | J1: Payment_Method | K1: Region | L1: Customer_Segment | M1: Customer_Since | N1: Total_Amount
A2: TRX0155 | B2: 45393 | C2: CUST023 | D2: Paul Baker | E2: P009 | F2: Monitor | G2: Electronics | H2: 3 | I2: 249.99 | J2: Cash | K2: Central | L2: Basic | M2: 44425 | N2: 749.97
A3: TRX0023 | B3: 45396 | C3: CUST013 | D3: Joseph Jackson | E3: P009 | F3: Monitor | G3: Electronics | H3: 3 | I3: 249.99 | J3: Credit Card | K3: Central | L3: Premium | M3: 44575 | N3: 749.97
A4: TRX0139 | B4: 45399 | C4: CUST021 | D4: Kevin Scott | E4: P005 | F4: Blender | G4: Appliances | H4: 3 | I4: 59.99 | J4: PayPal | K4: South | L4: Standard | M4: 45262 | N4: 179.97
A5: TRX0043 | B5: 45400 | C5: CUST046 | D5: Kathleen Bennett | E5: P005 | F5: Blender | G5: Appliances | H5: 3 | I5: 59.99 | J5: Cash | K5: North | L5: Premium | M5: 45114 | N5: 179.97
A6: TRX0212 | B6: 45400 | C6: CUST003 | D6: Michael Brown | E6: P008 | F6: Bookshelf | G6: Furniture | H6: 5 | I6: 149.99 | J6: Credit Card | K6: North | L6: Premium | M6: 45295 | N6: 749.95
A7: TRX0092 | B7: 45403 | C7: CUST024 | D7: Dorothy Nelson | E7: P005 | F7: Blender | G7: Appliances | H7: 2 | I7: 59.99 | J7: Cash | K7: West | L7: Standard | M7: 44746 | N7: 119.98
A8: TRX0193 | B8: 45403 | C8: CUST024 | D8: Dorothy Nelson | E8: P003 | F8: Headphones | G8: Electronics | H8: 5 | I8: 149.99 | J8: Credit Card | K8: Central | L8: Standard | M8: 44418 | N8: 749.95
A9: TRX0240 | B9: 45403 | C9: CUST017 | D9: Charles Allen | E9: P005 | F9: Blender | G9: Appliances | H9: 3 | I9: 59.99 | J9: Debit Card | K9: South | L9: Basic | M9: 45007 | N9: 179.97
A10: TRX0135 | B10: 45405 | C10: CUST009 | D10: Robert Thomas | E10: P001 | F10: Laptop | G10: Electronics | H10: 3 | I10: 899.99 | J10: PayPal | K10: East | L10: Standard | M10: 45299 | N10: 2699.97
A11: TRX0185 | B11: 45408 | C11: CUST026 | D11: Karen Hill | E11: P005 | F11: Blender | G11: Appliances | H11: 3 | I11: 59.99 | J11: Cash | K11: West | L11: Premium | M11: 45207 | N11: 179.97
A12: TRX0138 | B12: 45408 | C12: CUST022 | D12: Susan Green | E12: P008 | F12: Bookshelf | G12: Furniture | H12: 1 | I12: 149.99 | J12: Credit Card | K12: West | L12: Standard | M12: 45103 | N12: 149.99
A13: TRX0209 | B13: 45408 | C13: CUST046 | D13: Kathleen Bennett | E13: P008 | F13: Bookshelf | G13: Furniture | H13: 5 | I13: 149.99 | J13: Debit Card | K13: North | L13: Basic | M13: 44830 | N13: 749.95
... A251: TRX0064 | B251: 45758 | C251: CUST031 | D251: Steven Turner | E251: P010 | F251: Keyboard | G251: Electronics | H251: 3 | I251: 89.99 | J251: Debit Card | K251: North | L251: Premium | M251: 44878 | N251: 269.97

Sheet sheet1
A1: Column1
A3: Mean | B3: 296.67
A4: Standard Error | B4: 17.38168
A5: Median | B5: 149.99
A6: Mode | B6: 149.99
A7: Standard Deviation | B7: 274.82849
A8: Sample Variance | B8: 75530.7
A9: Kurtosis | B9: -0.001187064
A10: Skewness | B10: 1.2287172
A11: Range | B11: 840
A12: Minimum | B12: 59.99
A13: Maximum | B13: 899.99
A14: Sum | B14: 74167.5
A15: Count | B15: 250

Sheet linear_regression
A1: SUMMARY OUTPUT
A3: Regression Statistics
A4: Multiple R | B4: 0.83544893
A5: R Square | B5: 0.69797492
A6: Adjusted R Square | B6: 0.69675708
A7: Standard Error | B7: 568.54608
A8: Observations | B8: 250
A10: ANOVA
B11: df | C11: SS | D11: MS | E11: F | F11: Significance F
A12: Regression | B12: 1 | C12: 1.8525922e+08 | D12: 1.8525922e+08 | E12: 573.12386 | F12: 2.0274088e-66
A13: Residual | B13: 248 | C13: 80164673 | D13: 323244.65
A14: Total | B14: 249 | C14: 2.6542389e+08
B16: Coefficients | C16: Standard Error | D16: t Stat | E16: P-value | F16: Lower 95% | G16: Upper 95% | H16: Lower 95.0% | I16: Upper 95.0%
A17: Intercept | B17: -14.342533 | C17: 52.968753 | D17: -0.27077347 | E17: 0.78679049 | F17: -118.6685 | G17: 89.983434 | H17: -118.6685 | I17: 89.983434
A18: X Variable 1 | B18: 3.1385459 | C18: 0.13110047 | D18: 23.940005 | E18: 2.0274088e-66 | F18: 2.8803336 | G18: 3.3967582 | H18: 2.8803336 | I18: 3.3967582

Sheet Sheet4
A1: Date_Diffrence | B1: Timestamp | C1: Total_Revenue_Per_Person | D1: Unique_Customer_ID
A2: {=DATEDIF(Final_Project_Dataset!M2:M251,Final_Project_Dataset!B2:B251,"Y")} -> 2 | B2: =NOW() -> 46012.017 | C2: =SUMIF(Final_Project_Dataset!C2:C251,D:D,Final_Project_Dataset!N2:N251) -> 8309.74 | D2: {=_xlfn.UNIQUE(Final_Project_Dataset!C2:C251)} -> CUST023 | F2: Grand Total | G2: =SUM(Final_Project_Dataset!N2:N251) -> 229192.47 | I2: TOP SELLING PRODUCT | J2: {=INDEX(Final_Project_Dataset!F2:F251,MATCH(MAX(COUNTIF(Final_Project_Dataset!F2:F251,Final_Project_Dataset!F2:F251)),COUNTIF(Final_Project_Dataset!F2:F251,Final_Project_Dataset!F2:F251),0))} -> Bookshelf | K2: =COUNTIF(Final_Project_Dataset!F2:F251,"Bookshelf") -> 35
A3: 2 | B3: =NOW() -> 46012.017 | C3: =SUMIF(Final_Project_Dataset!C3:C252,D:D,Final_Project_Dataset!N3:N252) -> 6949.84 | D3: CUST013
A4: 0 | B4: =NOW() -> 46012.017 | C4: =SUMIF(Final_Project_Dataset!C4:C253,D:D,Final_Project_Dataset!N4:N253) -> 3259.87 | D4: CUST021
A5: 0 | B5: =NOW() -> 46012.017 | C5: =SUMIF(Final_Project_Dataset!C5:C254,D:D,Final_Project_Dataset!N5:N254) -> 4309.81 | D5: CUST046
A6: 0 | B6: =NOW() -> 46012.017 | C6: =SUMIF(Final_Project_Dataset!C6:C255,D:D,Final_Project_Dataset!N6:N255) -> 6169.74 | D6: CUST003
A7: 1 | B7: =NOW() -> 46012.017 | C7: =SUMIF(Final_Project_Dataset!C7:C256,D:D,Final_Project_Dataset!N7:N256) -> 8269.79 | D7: CUST024 | F7: FILTER FUNCTION
A8: 2 | B8: =NOW() -> 46012.017 | C8: =SUMIF(Final_Project_Dataset!C8:C257,D:D,Final_Project_Dataset!N8:N257) -> 5089.73 | D8: CUST017 | F8: {=_xlfn._xlws.FILTER(Final_Project_Dataset!A2:N251,(Final_Project_Dataset!F2:F251="LAPTOP")*(Final_Project_Dataset!L2:L251="PREMIUM"),"NO PREMIUM LAPTOP SALES FOUND")} -> TRX0041 | G8: 45432 | H8: CUST021 | I8: Kevin Scott | J8: P001 | K8: Laptop | L8: Electronics | M8: 1 | N8: 899.99 | O8: Credit Card | P8: West | Q8: Premium | R8: 44578 | S8: 899.99
A9: 1 | B9: =NOW() -> 46012.017 | C9: =SUMIF(Final_Project_Dataset!C9:C258,D:D,Final_Project_Dataset!N9:N258) -> 3509.9 | D9: CUST009 | F9: TRX0044 | G9: 45459 | H9: CUST029 | I9: Edward Mitchell | J9: P001 | K9: Laptop | L9: Electronics | M9: 5 | N9: 899.99 | O9: PayPal | P9: East | Q9: Premium | R9: 45278 | S9: 4499.95
A10: 0 | B10: =NOW() -> 46012.017 | C10: =SUMIF(Final_Project_Dataset!C10:C259,D:D,Final_Project_Dataset!N10:N259) -> 8009.77 | D10: CUST026 | F10: TRX0104 | G10: 45471 | H10: CUST012 | I10: Patricia Moore | J10: P001 | K10: Laptop | L10: Electronics | M10: 4 | N10: 899.99 | O10: Credit Card | P10: East | Q10: Premium | R10: 44993 | S10: 3599.96
A11: 0 | B11: =NOW() -> 46012.017 | C11: =SUMIF(Final_Project_Dataset!C11:C260,D:D,Final_Project_Dataset!N11:N260) -> 1979.89 | D11: CUST022 | F11: TRX0207 | G11: 45657 | H11: CUST025 | I11: Mark Carter | J11: P001 | K11: Laptop | L11: Electronics | M11: 1 | N11: 899.99 | O11: PayPal | P11: North | Q11: Premium | R11: 45050 | S11: 899.99
A12: 0 | B12: =NOW() -> 46012.017 | C12: =SUMIF(Final_Project_Dataset!C12:C261,D:D,Final_Project_Dataset!N12:N261) -> 5949.85 | D12: CUST041 | F12: TRX0016 | G12: 45724 | H12: CUST035 | I12: Harry Morgan | J12: P001 | K12: Laptop | L12: Electronics | M12: 5 | N12: 899.99 | O12: PayPal | P12: East | Q12: Premium | R12: 45389 | S12: 4499.95
A13: 1 | B13: =NOW() -> 46012.017 | C13: =SUMIF(Final_Project_Dataset!C13:C262,D:D,Final_Project_Dataset!N13:N262) -> 479.92 | D13: CUST043 | F13: TRX0124 | G13: 45737 | H13: CUST040 | I13: Sharon Butler | J13: P001 | K13: Laptop | L13: Electronics | M13: 3 | N13: 899.99 | O13: Debit Card | P13: North | Q13: Premium | R13: 44876 | S13: 2699.97
A14: 1 | B14: =NOW() -> 46012.017 | C14: =SUMIF(Final_Project_Dataset!C14:C263,D:D,Final_Project_Dataset!N14:N263) -> 4199.94 | D14: CUST038
A15: 0 | B15: =NOW() -> 46012.017 | C15: =SUMIF(Final_Project_Dataset!C15:C264,D:D,Final_Project_Dataset!N15:N264) -> 3779.93 | D15: CUST027
A16: 2 | B16: =NOW() -> 46012.017 | C16: =SUMIF(Final_Project_Dataset!C16:C265,D:D,Final_Project_Dataset!N16:N265) -> 15659.65 | D16: CUST025
A17: 1 | B17: =NOW() -> 46012.017 | C17: =SUMIF(Final_Project_Dataset!C17:C266,D:D,Final_Project_Dataset!N17:N266) -> 1909.93 | D17: CUST010
A18: 0 | B18: =NOW() -> 46012.017 | C18: =SUMIF(Final_Project_Dataset!C18:C267,D:D,Final_Project_Dataset!N18:N267) -> 4789.79 | D18: CUST048
A19: 1 | B19: =NOW() -> 46012.017 | C19: =SUMIF(Final_Project_Dataset!C19:C268,D:D,Final_Project_Dataset!N19:N268) -> 10649.8 | D19: CUST018
A20: 0 | B20: =NOW() -> 46012.017 | C20: =SUMIF(Final_Project_Dataset!C20:C269,D:D,Final_Project_Dataset!N20:N269) -> 9799.73 | D20: CUST012
A21: 0 | B21: =NOW() -> 46012.017 | C21: =SUMIF(Final_Project_Dataset!C21:C270,D:D,Final_Project_Dataset!N21:N270) -> 3769.83 | D21: CUST044
A22: 0 | B22: =NOW() -> 46012.017 | C22: =SUMIF(Final_Project_Dataset!C22:C271,D:D,Final_Project_Dataset!N22:N271) -> 4189.77 | D22: CUST036
A23: 2 | B23: =NOW() -> 46012.017 | C23: =SUMIF(Final_Project_Dataset!C23:C272,D:D,Final_Project_Dataset!N23:N272) -> 1289.9 | D23: CUST014
A24: 2 | B24: =NOW() -> 46012.017 | C24: =SUMIF(Final_Project_Dataset!C24:C273,D:D,Final_Project_Dataset!N24:N273) -> 6459.79 | D24: CUST030
A25: 1 | B25: =NOW() -> 46012.017 | C25: =SUMIF(Final_Project_Dataset!C25:C274,D:D,Final_Project_Dataset!N25:N274) -> 11919.77 | D25: CUST029
... A51: 1 | B51: =NOW() -> 46012.017 | C51: =SUMIF(Final_Project_Dataset!C51:C300,D:D,Final_Project_Dataset!N51:N300) -> 599.96 | D51: CUST001
A52: 0 | B52: =NOW() -> 46012.017
A53: 0 | B53: =NOW() -> 46012.017
A54: 0 | B54: =NOW() -> 46012.017
A55: 0 | B55: =NOW() -> 46012.017
A56: 0 | B56: =NOW() -> 46012.017
A57: 2 | B57: =NOW() -> 46012.017
A58: 1 | B58: =NOW() -> 46012.017
A59: 1 | B59: =NOW() -> 46012.017
A60: 1 | B60: =NOW() -> 46012.017
A61: 0 | B61: =NOW() -> 46012.017
A62: 1 | B62: =NOW() -> 46012.017
A63: 2 | B63: =NOW() -> 46012.017
... A251: 2 | B251: =NOW() -> 46012.017

Sheet TOP_5_CUSTOMER
A1: Customer_name | B1: Total_Amount
A2: {=_xlfn.UNIQUE(Final_Project_Dataset!D2:D251)} -> Paul Baker | B2: {=SUMIF(Final_Project_Dataset!D2:D251,_xlfn.ANCHORARRAY(A2),Final_Project_Dataset!N2:N251)} -> 8309.74 | D2: RANK | E2: TOP_REVENUE | F2: Customer_Name
A3: Joseph Jackson | B3: 6949.84 | D3: 1 | E3: =LARGE(A2:B51,D3) -> 15659.65 | F3: =INDEX(A2:B51,MATCH(E3,B2:B51,0),1) -> Mark Carter
A4: Kevin Scott | B4: 3259.87 | D4: 2 | E4: =LARGE(A3:B52,D4) -> 11919.77 | F4: =INDEX(A3:B52,MATCH(E4,B3:B52,0),1) -> Edward Mitchell
A5: Kathleen Bennett | B5: 4309.81 | D5: 3 | E5: =LARGE(A4:B53,D5) -> 10649.8 | F5: =INDEX(A4:B53,MATCH(E5,B4:B53,0),1) -> Barbara Young
A6: Michael Brown | B6: 6169.74 | D6: 4 | E6: =LARGE(A5:B54,D6) -> 9799.73 | F6: =INDEX(A5:B54,MATCH(E6,B5:B54,0),1) -> Patricia Moore
A7: Dorothy Nelson | B7: 8269.79 | D7: 5 | E7: =LARGE(A6:B55,D7) -> 8269.79 | F7: =INDEX(A6:B55,MATCH(E7,B6:B55,0),1) -> Dorothy Nelson
A8: Charles Allen | B8: 5089.73
A9: Robert Thomas | B9: 3509.9
A10: Karen Hill | B10: 8009.77
A11: Susan Green | B11: 1979.89
A12: Peter Richardson | B12: 5949.85
A13: Dennis Gray | B13: 479.92
A14: Michelle Rogers | B14: 4199.94
A15: George Adams | B15: 3779.93
A16: Mark Carter | B16: 15659.65
A17: Maria Garcia | B17: 1909.93
A18: Virginia Sanders | B18: 4789.79
A19: Barbara Young | B19: 10649.8
... A51: John Smith | B51: 599.96

Sheet OBJECTIVE1
A3: Row Labels | B3: Sum of Total_Amount
A4: Barbara Young | B4: 10649.8
A5: Edward Mitchell | B5: 11919.77
A6: Mark Carter | B6: 15659.65
A7: Patricia Moore | B7: 9799.73
A8: Paul Baker | B8: 8309.74
A9: Grand Total | B9: 56338.69

Sheet OBJECTIVE2
A3: Row Labels | B3: Sum of Unit_Price
A4: Appliances | B4: 2859.57
A5: Electronics | B5: 55258.69
A6: Furniture | B6: 16049.24
A7: Grand Total | B7: 74167.5

Sheet OBHECTIVE3
A3: Row Labels | B3: Sum of Quantity
A4: Blender | B4: 87
A5: Bookshelf | B5: 102
A6: Coffee Maker | B6: 39
A7: Desk | B7: 78
A8: Headphones | B8: 47
A9: Keyboard | B9: 89
A10: Laptop | B10: 75
A11: Monitor | B11: 88
A12: Office Chair | B12: 52
A13: Smartphone | B13: 96
A14: Grand Total | B14: 753

Sheet OBJECTIVE4
A3: Row Labels | B3: Count of Region
A4: 2021 | B4: 51
A5: 2022 | B5: 94
A6: 2023 | B6: 83
A7: 2024 | B7: 22
A8: Grand Total | B8: 250

Sheet OBJECTIVE5
A3: Row Labels | B3: Count of Payment_Method
A4: Jan | B4: 26
A5: Feb | B5: 20
A6: Mar | B6: 19
A7: Apr | B7: 28
A8: May | B8: 19
A9: Jun | B9: 19
A10: Jul | B10: 24
A11: Aug | B11: 18
A12: Sep | B12: 19
A13: Oct | B13: 16
A14: Nov | B14: 17
A15: Dec | B15: 25
A16: Grand Total | B16: 250
